bsxplorer/BamReader.py
bsxplorer/Base.py
bsxplorer/Binom.py
bsxplorer/ChrLevelsClass.py
bsxplorer/Clusters.py
bsxplorer/Config.py
bsxplorer/GenomeClass.py
bsxplorer/MetageneClasses.py
bsxplorer/Plots.py
bsxplorer/SeqMapper.py
bsxplorer/UniversalReader_batches.py
bsxplorer/UniversalReader_classes.py
bsxplorer/__init__.py
bsxplorer/cons_master.py
bsxplorer/cons_utils.py
bsxplorer/utils.py
bsxplorer/html/CategoryTemplate.html
bsxplorer/html/ChrLevelsTemplate.html
bsxplorer/html/MetageneTemplate.html
bsxplorer-1.1.0.post2.dist-info/METADATA
bsxplorer-1.1.0.post2.dist-info/WHEEL
bsxplorer-1.1.0.post2.dist-info/entry_points.txt
bsxplorer-1.1.0.post2.dist-info/licenses/LICENSE.txt
bsxplorer-1.1.0.post2.dist-info/RECORD
