Metadata-Version: 2.4
Name: bsxplorer
Version: 1.1.0.post2
Summary: Analytical framework for BS-seq data comparison and visualization
Project-URL: Homepage, https://github.com/shitohana/BSXplorer
Project-URL: Repository, https://github.com/shitohana/BSXplorer
Project-URL: Documentation, https://shitohana.github.io/BSXplorer/
Project-URL: Issues, https://github.com/shitohana/BSXplorer/issues
Author-email: Konstantin Y <kyudytskiy@gmail.com>
License: MIT License
License-File: LICENSE.txt
Keywords: bismark,bs-seq,methylation,plot
Classifier: Development Status :: 5 - Production/Stable
Classifier: License :: OSI Approved :: GNU General Public License v3 (GPLv3)
Classifier: Operating System :: OS Independent
Classifier: Programming Language :: Python :: 3.10
Classifier: Topic :: Scientific/Engineering
Classifier: Topic :: Scientific/Engineering :: Bio-Informatics
Requires-Python: >=3.10
Requires-Dist: bio==1.6.*
Requires-Dist: biopython==1.*
Requires-Dist: dynamictreecut==0.*
Requires-Dist: fastcluster==1.2.*
Requires-Dist: func-timeout==4.*
Requires-Dist: jinja2==3.1.*
Requires-Dist: matplotlib~=3.8
Requires-Dist: numba==0.*
Requires-Dist: numpy==1.*
Requires-Dist: packaging==23.*
Requires-Dist: pandas==2.2.*
Requires-Dist: plotly==5.*
Requires-Dist: polars==0.20
Requires-Dist: progress==1.*
Requires-Dist: psutil==5.*
Requires-Dist: pyarrow==14.*
Requires-Dist: pyreadr>=0.4
Requires-Dist: pysam==0.22.*
Requires-Dist: scikit-learn==1.4.*
Requires-Dist: scipy==1.14.*
Requires-Dist: seaborn==0.*
